lesana/__init__.py
lesana/_version.py
lesana/collection.py
lesana/command.py
lesana/templating.py
lesana/types.py
lesana/data/__init__.py
lesana/data/post-checkout
lesana/data/settings.yaml
lesana-0.10.1.dist-info/METADATA
lesana-0.10.1.dist-info/WHEEL
lesana-0.10.1.dist-info/entry_points.txt
lesana-0.10.1.dist-info/top_level.txt
lesana-0.10.1.dist-info/RECORD
