Metadata-Version: 2.1
Name: lesana
Version: 0.10.1
Summary: Manage collection inventories throught yaml files.
Author-email: Elena ``of Valhalla'' Grandi <valhalla@trueelena.org>
License: AGPLv3+
Project-URL: Homepage, https://lesana.trueelena.org/
Project-URL: Documentation, https://lesana.trueelena.org/
Project-URL: Repository, https://git.sr.ht/~valhalla/lesana
Project-URL: Source, https://git.sr.ht/~valhalla/lesana
Project-URL: Issues, https://todo.sr.ht/~valhalla/lesana
Project-URL: Tracker, https://todo.sr.ht/~valhalla/lesana
Project-URL: Changelog, https://git.sr.ht/~valhalla/lesana/tree/master/item/CHANGELOG.rst
Project-URL: Mailing lists, https://sr.ht/~valhalla/lesana/lists
Keywords: collection,inventory
Classifier: Development Status :: 3 - Alpha
Classifier: Environment :: Console
Classifier: Intended Audience :: Developers
Classifier: Intended Audience :: End Users/Desktop
Classifier: License :: OSI Approved :: GNU Affero General Public License v3 or later (AGPLv3+)
Classifier: Operating System :: POSIX
Classifier: Programming Language :: Python :: 3
Classifier: Programming Language :: Python :: 3.8
Classifier: Programming Language :: Python :: 3.9
Classifier: Programming Language :: Python :: 3.10
Classifier: Programming Language :: Python :: 3.11
Classifier: Programming Language :: Python :: 3.12
Classifier: Topic :: Software Development :: Libraries :: Python Modules
Classifier: Topic :: Utilities
Requires-Python: >=3.8
Requires-Dist: ruamel.yaml
Requires-Dist: jinja2
Requires-Dist: python-dateutil
Provides-Extra: cli
Requires-Dist: hazwaz ; extra == 'cli'
